rust_graph-0.1.1.dist-info/METADATA
rust_graph-0.1.1.dist-info/WHEEL
rust_graph-0.1.1.dist-info/licenses/LICENSE
rust_graph.libs/libgcc_s-1e52349c.so.1
rust_graph/py.typed
rust_graph/__init__.py
rust_graph/rust_graph.pyi
rust_graph/rust_graph.cpython-313-x86_64-linux-musl.so
rust_graph-0.1.1.dist-info/RECORD
