Metadata-Version: 2.4
Name: rust-graph
Version: 0.1.1
Classifier: Programming Language :: Rust
Classifier: Programming Language :: Python :: Implementation :: CPython
Classifier: Programming Language :: Python :: Implementation :: PyPy
Classifier: Programming Language :: Python
Classifier: Programming Language :: Python :: 3
Classifier: Programming Language :: Python :: 3.8
Classifier: Programming Language :: Python :: 3.9
Classifier: Programming Language :: Python :: 3.10
Classifier: Programming Language :: Python :: 3.11
Classifier: Programming Language :: Python :: 3.12
Classifier: Programming Language :: Python :: 3.13
Classifier: License :: OSI Approved :: Apache Software License
License-File: LICENSE
Summary: Simple and fast graph operations written in Rust
Author: Kiyoon Kim
License: Apache-2.0
Requires-Python: >=3.8, <4
Project-URL: Homepage, https://github.com/deargen/rust-graph
